claudesync/__init__.py
claudesync/chat_sync.py
claudesync/compression.py
claudesync/exceptions.py
claudesync/provider_factory.py
claudesync/session_key_manager.py
claudesync/syncmanager.py
claudesync/utils.py
claudesync/cli/__init__.py
claudesync/cli/auth.py
claudesync/cli/category.py
claudesync/cli/chat.py
claudesync/cli/config.py
claudesync/cli/file.py
claudesync/cli/main.py
claudesync/cli/organization.py
claudesync/cli/project.py
claudesync/cli/session.py
claudesync/cli/submodule.py
claudesync/cli/sync.py
claudesync/configmanager/__init__.py
claudesync/configmanager/base_config_manager.py
claudesync/configmanager/file_config_manager.py
claudesync/configmanager/inmemory_config_manager.py
claudesync/providers/__init__.py
claudesync/providers/base_claude_ai.py
claudesync/providers/base_provider.py
claudesync/providers/claude_ai.py
claudesync-0.7.4.dist-info/licenses/LICENSE
claudesync-0.7.4.dist-info/METADATA
claudesync-0.7.4.dist-info/WHEEL
claudesync-0.7.4.dist-info/entry_points.txt
claudesync-0.7.4.dist-info/top_level.txt
claudesync-0.7.4.dist-info/RECORD
