Metadata-Version: 2.4
Name: claudesync
Version: 0.7.4
Summary: A tool to synchronize local files with Claude.ai projects
Author-email: Jahziah Wagner <540380+jahwag@users.noreply.github.com>
License: MIT License
Project-URL: Homepage, https://github.com/jahwag/claudesync
Project-URL: Bug Tracker, https://github.com/jahwag/claudesync/issues
Keywords: sync,files,Claude.ai,automation,synchronization,project management,file management,cloud sync,cli tool,command line,productivity,development tools,file synchronization,continuous integration,devops,version control
Classifier: Programming Language :: Python :: 3
Classifier: License :: OSI Approved :: MIT License
Classifier: Operating System :: OS Independent
Requires-Python: >=3.10
License-File: LICENSE
Requires-Dist: click>=8.1.7
Requires-Dist: click_completion>=0.5.2
Requires-Dist: pathspec>=0.12.1
Requires-Dist: pytest>=8.3.2
Requires-Dist: python_crontab>=3.2.0
Requires-Dist: setuptools>=73.0.1
Requires-Dist: sseclient_py>=1.8.0
Requires-Dist: tqdm>=4.66.5
Requires-Dist: pytest-cov>=5.0.0
Requires-Dist: crontab>=1.0.1
Requires-Dist: python-crontab>=3.2.0
Requires-Dist: Brotli>=1.1.0
Requires-Dist: cryptography>=42.0.4
Provides-Extra: test
Requires-Dist: pytest>=8.2.2; extra == "test"
Requires-Dist: pytest-cov>=5.0.0; extra == "test"
Dynamic: license-file
